studentvue/StudentVue.py
studentvue/__init__.py
studentvue-2.0.5.dist-info/LICENSE
studentvue-2.0.5.dist-info/METADATA
studentvue-2.0.5.dist-info/WHEEL
studentvue-2.0.5.dist-info/top_level.txt
studentvue-2.0.5.dist-info/RECORD
