Metadata-Version: 2.1
Name: studentvue
Version: 2.0.5
Summary: Python StudentVue Library
Home-page: https://github.com/StudentVue/StudentVue.py
Author: Kai Chang
License: MIT
Platform: UNKNOWN
